ocx_generator/__init__.py
ocx_generator/cli.py
ocx_generator/generator.py
ocx_generator/utils/__init__.py
ocx_generator/utils/logging.py
ocx_generator-2.4.0.dist-info/LICENSE
ocx_generator-2.4.0.dist-info/METADATA
ocx_generator-2.4.0.dist-info/WHEEL
ocx_generator-2.4.0.dist-info/entry_points.txt
ocx_generator-2.4.0.dist-info/RECORD
