Metadata-Version: 2.1
Name: ocx_generator
Version: 2.4.0
Summary: Python CLI for managing OCX schema databinding and versioning according to PEP 440.
Author: ocastrup
Author-email: ole.christian.astrup@dnv.com
Requires-Python: >=3.11,<4.0
Classifier: Programming Language :: Python :: 3
Classifier: Programming Language :: Python :: 3.11
Requires-Dist: click
Requires-Dist: loguru
Requires-Dist: lxml
Requires-Dist: packaging (>=23.1,<24.0)
Requires-Dist: soap
Requires-Dist: tbump
Requires-Dist: typer
Requires-Dist: xsdata
